<?xml version="1.0" encoding="utf-8" ?>
<c2eventsheet>
    <!--All the 'name' attributes are ignored by Construct 2 - they are there for readability only.-->
    <name>evt_Jogo</name>
    <events>
        <event-group description="" sid="373688101835326" title="Luz+Porta">
            <sub-events>
                <event-group description="" sid="982334713401362" title="Porta">
                    <sub-events>
                        <event-group description="" sid="612056590050042" title="Ativar/DesativarP">
                            <sub-events>
                                <event-block sid="689208137944702">
                                    <conditions>
                                        <condition id="17" name="On tap object" sid="765637685370108" type="Touch">
                                            <param id="0" name="Object">OBJ_ButtonDoorLeft1</param>
                                        </condition>
                                        <condition id="-9" inverted="1" name="Layer is visible" sid="178055338087368" type="System">
                                            <param id="0" name="Layer">2</param>
                                        </condition>
                                        <condition id="-7" name="Compare instance variable" sid="685561612430606" type="Hora">
                                            <param id="0" name="Instance variable">Hora</param>
                                            <param id="1" name="Comparison">1</param>
                                            <param id="2" name="Value">6</param>
                                        </condition>
                                    </conditions>
                                    <actions />
                                    <sub-events>
                                        <event-block sid="516252426735862">
                                            <conditions>
                                                <condition id="-7" name="Compare instance variable" sid="823499323977030" type="OBJ_ButtonDoorLeft1">
                                                    <param id="0" name="Instance variable">Porta</param>
                                                    <param id="1" name="Comparison">0</param>
                                                    <param id="2" name="Value">0</param>
                                                </condition>
                                                <condition id="3" name="Compare frame" sid="709477897707686" type="Spr_PortaLeft">
                                                    <param id="0" name="Comparison">0</param>
                                                    <param id="1" name="Number">0</param>
                                                </condition>
                                                <condition id="2" name="Is playing" sid="724267079774629" type="Spr_PortaLeft">
                                                    <param id="0" name="Animation">&quot;FrameInutilMasNDeleta&quot;</param>
                                                </condition>
                                            </conditions>
                                            <actions>
                                                <action id="4" name="Set animation" sid="184153005322884" type="Spr_PortaLeft">
                                                    <param id="0" name="Animation">&quot;PortaFecha&quot;</param>
                                                    <param id="1" name="From">1</param>
                                                </action>
                                                <action id="-10" name="Set value" sid="694389160184227" type="OBJ_ButtonDoorLeft1">
                                                    <param id="0" name="Instance variable">Porta</param>
                                                    <param id="1" name="Value">1</param>
                                                </action>
                                                <action id="0" name="Play" sid="762667702230249" type="Audio">
                                                    <param id="0" name="Audio file">Door</param>
                                                    <param id="2" name="Loop">0</param>
                                                    <param id="3" name="Volume">0</param>
                                                    <param id="1" name="Tag (optional)">&quot;&quot;</param>
                                                </action>
                                                <action id="-11" name="Add to" sid="386062395571893" type="UsoDeEnergiaPRGS">
                                                    <param id="0" name="Instance variable">NivelEnergia</param>
                                                    <param id="1" name="Value">1</param>
                                                </action>
                                            </actions>
                                        </event-block>
                                        <event-block sid="935593326870044">
                                            <conditions>
                                                <condition id="-7" name="Compare instance variable" sid="149503308005881" type="OBJ_ButtonDoorLeft1">
                                                    <param id="0" name="Instance variable">Porta</param>
                                                    <param id="1" name="Comparison">0</param>
                                                    <param id="2" name="Value">0</param>
                                                </condition>
                                                <condition id="3" name="Compare frame" sid="139159051048440" type="Spr_PortaLeft">
                                                    <param id="0" name="Comparison">0</param>
                                                    <param id="1" name="Number">12</param>
                                                </condition>
                                                <condition id="2" name="Is playing" sid="706216474738458" type="Spr_PortaLeft">
                                                    <param id="0" name="Animation">&quot;PortaAbre&quot;</param>
                                                </condition>
                                            </conditions>
                                            <actions>
                                                <action id="4" name="Set animation" sid="653506386990229" type="Spr_PortaLeft">
                                                    <param id="0" name="Animation">&quot;PortaFecha&quot;</param>
                                                    <param id="1" name="From">1</param>
                                                </action>
                                                <action id="-10" name="Set value" sid="268304332382430" type="OBJ_ButtonDoorLeft1">
                                                    <param id="0" name="Instance variable">Porta</param>
                                                    <param id="1" name="Value">1</param>
                                                </action>
                                                <action id="0" name="Play" sid="223987546622111" type="Audio">
                                                    <param id="0" name="Audio file">Door</param>
                                                    <param id="2" name="Loop">0</param>
                                                    <param id="3" name="Volume">0</param>
                                                    <param id="1" name="Tag (optional)">&quot;&quot;</param>
                                                </action>
                                                <action id="-11" name="Add to" sid="656793128207720" type="UsoDeEnergiaPRGS">
                                                    <param id="0" name="Instance variable">NivelEnergia</param>
                                                    <param id="1" name="Value">1</param>
                                                </action>
                                            </actions>
                                        </event-block>
                                        <event-block sid="889426351318152">
                                            <conditions>
                                                <condition id="-7" name="Compare instance variable" sid="543639777087187" type="OBJ_ButtonDoorLeft1">
                                                    <param id="0" name="Instance variable">Porta</param>
                                                    <param id="1" name="Comparison">0</param>
                                                    <param id="2" name="Value">1</param>
                                                </condition>
                                                <condition id="3" name="Compare frame" sid="633622170348390" type="Spr_PortaLeft">
                                                    <param id="0" name="Comparison">0</param>
                                                    <param id="1" name="Number">12</param>
                                                </condition>
                                                <condition id="2" name="Is playing" sid="325453608052441" type="Spr_PortaLeft">
                                                    <param id="0" name="Animation">&quot;PortaFecha&quot;</param>
                                                </condition>
                                            </conditions>
                                            <actions>
                                                <action id="4" name="Set animation" sid="344447612126214" type="Spr_PortaLeft">
                                                    <param id="0" name="Animation">&quot;PortaAbre&quot;</param>
                                                    <param id="1" name="From">1</param>
                                                </action>
                                                <action id="-10" name="Set value" sid="420724533005047" type="OBJ_ButtonDoorLeft1">
                                                    <param id="0" name="Instance variable">Porta</param>
                                                    <param id="1" name="Value">0</param>
                                                </action>
                                                <action id="0" name="Play" sid="317419165179562" type="Audio">
                                                    <param id="0" name="Audio file">Door</param>
                                                    <param id="2" name="Loop">0</param>
                                                    <param id="3" name="Volume">0</param>
                                                    <param id="1" name="Tag (optional)">&quot;&quot;</param>
                                                </action>
                                                <action id="-12" name="Subtract from" sid="586454970956960" type="UsoDeEnergiaPRGS">
                                                    <param id="0" name="Instance variable">NivelEnergia</param>
                                                    <param id="1" name="Value">1</param>
                                                </action>
                                            </actions>
                                        </event-block>
                                    </sub-events>
                                </event-block>
                                <event-block sid="691999428713716">
                                    <conditions>
                                        <condition id="17" name="On tap object" sid="704418686887634" type="Touch">
                                            <param id="0" name="Object">OBJ_ButtonDoorRight1</param>
                                        </condition>
                                        <condition id="-9" inverted="1" name="Layer is visible" sid="781363866910270" type="System">
                                            <param id="0" name="Layer">2</param>
                                        </condition>
                                        <condition id="-7" name="Compare instance variable" sid="892231549720750" type="Hora">
                                            <param id="0" name="Instance variable">Hora</param>
                                            <param id="1" name="Comparison">1</param>
                                            <param id="2" name="Value">6</param>
                                        </condition>
                                    </conditions>
                                    <actions />
                                    <sub-events>
                                        <event-block sid="893820118139707">
                                            <conditions>
                                                <condition id="-7" name="Compare instance variable" sid="609922664964017" type="OBJ_ButtonDoorRight1">
                                                    <param id="0" name="Instance variable">porta</param>
                                                    <param id="1" name="Comparison">0</param>
                                                    <param id="2" name="Value">0</param>
                                                </condition>
                                                <condition id="3" name="Compare frame" sid="291577148982322" type="Spr_PortaRight1">
                                                    <param id="0" name="Comparison">0</param>
                                                    <param id="1" name="Number">0</param>
                                                </condition>
                                                <condition id="2" name="Is playing" sid="473425646605896" type="Spr_PortaRight1">
                                                    <param id="0" name="Animation">&quot;FrameInutilMasNDeleta&quot;</param>
                                                </condition>
                                            </conditions>
                                            <actions>
                                                <action id="4" name="Set animation" sid="937638915281474" type="Spr_PortaRight1">
                                                    <param id="0" name="Animation">&quot;PortaFecha&quot;</param>
                                                    <param id="1" name="From">1</param>
                                                </action>
                                                <action id="-10" name="Set value" sid="905549838179088" type="OBJ_ButtonDoorRight1">
                                                    <param id="0" name="Instance variable">porta</param>
                                                    <param id="1" name="Value">1</param>
                                                </action>
                                                <action id="0" name="Play" sid="965825804591042" type="Audio">
                                                    <param id="0" name="Audio file">Door</param>
                                                    <param id="2" name="Loop">0</param>
                                                    <param id="3" name="Volume">0</param>
                                                    <param id="1" name="Tag (optional)">&quot;&quot;</param>
                                                </action>
                                                <action id="-11" name="Add to" sid="955265796675389" type="UsoDeEnergiaPRGS">
                                                    <param id="0" name="Instance variable">NivelEnergia</param>
                                                    <param id="1" name="Value">1</param>
                                                </action>
                                            </actions>
                                        </event-block>
                                        <event-block sid="706773091974058">
                                            <conditions>
                                                <condition id="-7" name="Compare instance variable" sid="894200178879230" type="OBJ_ButtonDoorRight1">
                                                    <param id="0" name="Instance variable">porta</param>
                                                    <param id="1" name="Comparison">0</param>
                                                    <param id="2" name="Value">0</param>
                                                </condition>
                                                <condition id="3" name="Compare frame" sid="534951495029908" type="Spr_PortaRight1">
                                                    <param id="0" name="Comparison">0</param>
                                                    <param id="1" name="Number">12</param>
                                                </condition>
                                                <condition id="2" name="Is playing" sid="664157367131797" type="Spr_PortaRight1">
                                                    <param id="0" name="Animation">&quot;PortaAbre&quot;</param>
                                                </condition>
                                            </conditions>
                                            <actions>
                                                <action id="4" name="Set animation" sid="107339256311883" type="Spr_PortaRight1">
                                                    <param id="0" name="Animation">&quot;PortaFecha&quot;</param>
                                                    <param id="1" name="From">1</param>
                                                </action>
                                                <action id="-10" name="Set value" sid="729843342880018" type="OBJ_ButtonDoorRight1">
                                                    <param id="0" name="Instance variable">porta</param>
                                                    <param id="1" name="Value">1</param>
                                                </action>
                                                <action id="-11" name="Add to" sid="933724831787385" type="UsoDeEnergiaPRGS">
                                                    <param id="0" name="Instance variable">NivelEnergia</param>
                                                    <param id="1" name="Value">1</param>
                                                </action>
                                                <action id="0" name="Play" sid="977502949729020" type="Audio">
                                                    <param id="0" name="Audio file">Door</param>
                                                    <param id="2" name="Loop">0</param>
                                                    <param id="3" name="Volume">0</param>
                                                    <param id="1" name="Tag (optional)">&quot;&quot;</param>
                                                </action>
                                            </actions>
                                        </event-block>
                                        <event-block sid="631311387811143">
                                            <conditions>
                                                <condition id="-7" name="Compare instance variable" sid="551087688775442" type="OBJ_ButtonDoorRight1">
                                                    <param id="0" name="Instance variable">porta</param>
                                                    <param id="1" name="Comparison">0</param>
                                                    <param id="2" name="Value">1</param>
                                                </condition>
                                                <condition id="3" name="Compare frame" sid="850962422085789" type="Spr_PortaRight1">
                                                    <param id="0" name="Comparison">0</param>
                                                    <param id="1" name="Number">12</param>
                                                </condition>
                                                <condition id="2" name="Is playing" sid="890702339270931" type="Spr_PortaRight1">
                                                    <param id="0" name="Animation">&quot;PortaFecha&quot;</param>
                                                </condition>
                                            </conditions>
                                            <actions>
                                                <action id="4" name="Set animation" sid="764706218367420" type="Spr_PortaRight1">
                                                    <param id="0" name="Animation">&quot;PortaAbre&quot;</param>
                                                    <param id="1" name="From">1</param>
                                                </action>
                                                <action id="-10" name="Set value" sid="984343839789801" type="OBJ_ButtonDoorRight1">
                                                    <param id="0" name="Instance variable">porta</param>
                                                    <param id="1" name="Value">0</param>
                                                </action>
                                                <action id="0" name="Play" sid="457144662869798" type="Audio">
                                                    <param id="0" name="Audio file">Door</param>
                                                    <param id="2" name="Loop">0</param>
                                                    <param id="3" name="Volume">0</param>
                                                    <param id="1" name="Tag (optional)">&quot;&quot;</param>
                                                </action>
                                                <action id="-12" name="Subtract from" sid="893047651040063" type="UsoDeEnergiaPRGS">
                                                    <param id="0" name="Instance variable">NivelEnergia</param>
                                                    <param id="1" name="Value">1</param>
                                                </action>
                                            </actions>
                                        </event-block>
                                    </sub-events>
                                </event-block>
                            </sub-events>
                        </event-group>
                    </sub-events>
                </event-group>
                <event-group description="" sid="657794897116889" title="Luz">
                    <sub-events>
                        <event-group description="" sid="188160637878890" title="Ativar/Desativar">
                            <sub-events>
                                <event-block sid="315682692550950">
                                    <conditions>
                                        <condition id="17" name="On tap object" sid="147715658468960" type="Touch">
                                            <param id="0" name="Object">OBJ_ButtonDoorLeft2</param>
                                        </condition>
                                        <condition id="-9" inverted="1" name="Layer is visible" sid="930872414532867" type="System">
                                            <param id="0" name="Layer">2</param>
                                        </condition>
                                        <condition id="-7" name="Compare instance variable" sid="561558397829861" type="Hora">
                                            <param id="0" name="Instance variable">Hora</param>
                                            <param id="1" name="Comparison">1</param>
                                            <param id="2" name="Value">6</param>
                                        </condition>
                                    </conditions>
                                    <actions />
                                    <sub-events>
                                        <event-block sid="104040724536503">
                                            <conditions>
                                                <condition id="-7" name="Compare instance variable" sid="197661841155335" type="Spr_Office">
                                                    <param id="0" name="Instance variable">ladodaluz</param>
                                                    <param id="1" name="Comparison">1</param>
                                                    <param id="2" name="Value">1</param>
                                                </condition>
                                            </conditions>
                                            <actions>
                                                <action id="-16" name="Wait" sid="516801161228980" type="System">
                                                    <param id="0" name="Seconds">0.1</param>
                                                </action>
                                                <action id="-10" name="Set value" sid="166437514163513" type="Spr_Office">
                                                    <param id="0" name="Instance variable">ladodaluz</param>
                                                    <param id="1" name="Value">1</param>
                                                </action>
                                                <action id="-11" name="Add to" sid="820891606877787" type="UsoDeEnergiaPRGS">
                                                    <param id="0" name="Instance variable">NivelEnergia</param>
                                                    <param id="1" name="Value">1</param>
                                                </action>
                                            </actions>
                                        </event-block>
                                        <event-block sid="224545114885259">
                                            <conditions>
                                                <condition id="-7" name="Compare instance variable" sid="288184273350585" type="Spr_Office">
                                                    <param id="0" name="Instance variable">ladodaluz</param>
                                                    <param id="1" name="Comparison">0</param>
                                                    <param id="2" name="Value">1</param>
                                                </condition>
                                            </conditions>
                                            <actions>
                                                <action id="-16" name="Wait" sid="837841037852678" type="System">
                                                    <param id="0" name="Seconds">0.1</param>
                                                </action>
                                                <action id="-10" name="Set value" sid="683889309464233" type="Spr_Office">
                                                    <param id="0" name="Instance variable">ladodaluz</param>
                                                    <param id="1" name="Value">0</param>
                                                </action>
                                                <action id="-12" name="Subtract from" sid="295703800320839" type="UsoDeEnergiaPRGS">
                                                    <param id="0" name="Instance variable">NivelEnergia</param>
                                                    <param id="1" name="Value">1</param>
                                                </action>
                                            </actions>
                                        </event-block>
                                        <event-block sid="649758714453257">
                                            <conditions>
                                                <condition id="-7" name="Compare instance variable" sid="792492757532657" type="Spr_Office">
                                                    <param id="0" name="Instance variable">ladodaluz</param>
                                                    <param id="1" name="Comparison">0</param>
                                                    <param id="2" name="Value">2</param>
                                                </condition>
                                            </conditions>
                                            <actions>
                                                <action id="-12" name="Subtract from" sid="983420250271408" type="UsoDeEnergiaPRGS">
                                                    <param id="0" name="Instance variable">NivelEnergia</param>
                                                    <param id="1" name="Value">1</param>
                                                </action>
                                            </actions>
                                        </event-block>
                                    </sub-events>
                                </event-block>
                                <event-block sid="696245491421474">
                                    <conditions>
                                        <condition id="17" name="On tap object" sid="191240223116711" type="Touch">
                                            <param id="0" name="Object">OBJ_ButtonDoorRight2</param>
                                        </condition>
                                        <condition id="-9" inverted="1" name="Layer is visible" sid="215516087357220" type="System">
                                            <param id="0" name="Layer">2</param>
                                        </condition>
                                        <condition id="-7" name="Compare instance variable" sid="842059177784514" type="Hora">
                                            <param id="0" name="Instance variable">Hora</param>
                                            <param id="1" name="Comparison">1</param>
                                            <param id="2" name="Value">6</param>
                                        </condition>
                                    </conditions>
                                    <actions />
                                    <sub-events>
                                        <event-block sid="844839546769528">
                                            <conditions>
                                                <condition id="-7" name="Compare instance variable" sid="421180215977178" type="Spr_Office">
                                                    <param id="0" name="Instance variable">ladodaluz</param>
                                                    <param id="1" name="Comparison">1</param>
                                                    <param id="2" name="Value">2</param>
                                                </condition>
                                            </conditions>
                                            <actions>
                                                <action id="-16" name="Wait" sid="666005301147977" type="System">
                                                    <param id="0" name="Seconds">0.1</param>
                                                </action>
                                                <action id="-10" name="Set value" sid="762615929520300" type="Spr_Office">
                                                    <param id="0" name="Instance variable">ladodaluz</param>
                                                    <param id="1" name="Value">2</param>
                                                </action>
                                                <action id="-11" name="Add to" sid="122475635887920" type="UsoDeEnergiaPRGS">
                                                    <param id="0" name="Instance variable">NivelEnergia</param>
                                                    <param id="1" name="Value">1</param>
                                                </action>
                                            </actions>
                                        </event-block>
                                        <event-block sid="559695737386577">
                                            <conditions>
                                                <condition id="-7" name="Compare instance variable" sid="713066113189668" type="Spr_Office">
                                                    <param id="0" name="Instance variable">ladodaluz</param>
                                                    <param id="1" name="Comparison">0</param>
                                                    <param id="2" name="Value">2</param>
                                                </condition>
                                            </conditions>
                                            <actions>
                                                <action id="-16" name="Wait" sid="218106584675649" type="System">
                                                    <param id="0" name="Seconds">0.1</param>
                                                </action>
                                                <action id="-10" name="Set value" sid="152469352116410" type="Spr_Office">
                                                    <param id="0" name="Instance variable">ladodaluz</param>
                                                    <param id="1" name="Value">0</param>
                                                </action>
                                                <action id="-12" name="Subtract from" sid="620521016455153" type="UsoDeEnergiaPRGS">
                                                    <param id="0" name="Instance variable">NivelEnergia</param>
                                                    <param id="1" name="Value">1</param>
                                                </action>
                                            </actions>
                                        </event-block>
                                        <event-block sid="821504707760098">
                                            <conditions>
                                                <condition id="-7" name="Compare instance variable" sid="105371326647620" type="Spr_Office">
                                                    <param id="0" name="Instance variable">ladodaluz</param>
                                                    <param id="1" name="Comparison">0</param>
                                                    <param id="2" name="Value">1</param>
                                                </condition>
                                            </conditions>
                                            <actions>
                                                <action id="-12" name="Subtract from" sid="681117413193429" type="UsoDeEnergiaPRGS">
                                                    <param id="0" name="Instance variable">NivelEnergia</param>
                                                    <param id="1" name="Value">1</param>
                                                </action>
                                            </actions>
                                        </event-block>
                                    </sub-events>
                                </event-block>
                            </sub-events>
                        </event-group>
                    </sub-events>
                </event-group>
                <event-block sid="451535109897142">
                    <conditions>
                        <condition id="-7" name="Compare instance variable" sid="151039057460653" type="Spr_Office">
                            <param id="0" name="Instance variable">ladodaluz</param>
                            <param id="1" name="Comparison">0</param>
                            <param id="2" name="Value">0</param>
                        </condition>
                    </conditions>
                    <actions>
                        <action id="4" name="Set animation" sid="438913363869215" type="Spr_Office">
                            <param id="0" name="Animation">&quot;Default&quot;</param>
                            <param id="1" name="From">1</param>
                        </action>
                    </actions>
                    <sub-events>
                        <event-block sid="876352285561732">
                            <conditions>
                                <condition id="-7" name="Compare instance variable" sid="412984785756646" type="OBJ_ButtonDoorLeft1">
                                    <param id="0" name="Instance variable">Porta</param>
                                    <param id="1" name="Comparison">0</param>
                                    <param id="2" name="Value">0</param>
                                </condition>
                            </conditions>
                            <actions>
                                <action id="4" name="Set animation" sid="695997843025468" type="Spr_LeftBotoes">
                                    <param id="0" name="Animation">&quot;Default&quot;</param>
                                    <param id="1" name="From">1</param>
                                </action>
                            </actions>
                        </event-block>
                        <event-block sid="792752037320914">
                            <conditions>
                                <condition id="-7" name="Compare instance variable" sid="528056376882485" type="OBJ_ButtonDoorLeft1">
                                    <param id="0" name="Instance variable">Porta</param>
                                    <param id="1" name="Comparison">0</param>
                                    <param id="2" name="Value">1</param>
                                </condition>
                            </conditions>
                            <actions>
                                <action id="4" name="Set animation" sid="636130702044179" type="Spr_LeftBotoes">
                                    <param id="0" name="Animation">&quot;OnlyDoor&quot;</param>
                                    <param id="1" name="From">1</param>
                                </action>
                            </actions>
                        </event-block>
                        <event-block sid="710441193431180">
                            <conditions>
                                <condition id="-7" name="Compare instance variable" sid="725873823064173" type="OBJ_ButtonDoorRight1">
                                    <param id="0" name="Instance variable">porta</param>
                                    <param id="1" name="Comparison">0</param>
                                    <param id="2" name="Value">0</param>
                                </condition>
                            </conditions>
                            <actions>
                                <action id="4" name="Set animation" sid="636327792731762" type="Spr_RightBotoes">
                                    <param id="0" name="Animation">&quot;Default&quot;</param>
                                    <param id="1" name="From">1</param>
                                </action>
                            </actions>
                        </event-block>
                        <event-block sid="734333452315256">
                            <conditions>
                                <condition id="-7" name="Compare instance variable" sid="170038231227217" type="OBJ_ButtonDoorRight1">
                                    <param id="0" name="Instance variable">porta</param>
                                    <param id="1" name="Comparison">0</param>
                                    <param id="2" name="Value">1</param>
                                </condition>
                            </conditions>
                            <actions>
                                <action id="4" name="Set animation" sid="969808893803941" type="Spr_RightBotoes">
                                    <param id="0" name="Animation">&quot;OnlyDoor&quot;</param>
                                    <param id="1" name="From">1</param>
                                </action>
                            </actions>
                        </event-block>
                    </sub-events>
                </event-block>
                <event-block sid="744612379757762">
                    <conditions>
                        <condition id="-7" name="Compare instance variable" sid="757264975011195" type="Spr_Office">
                            <param id="0" name="Instance variable">ladodaluz</param>
                            <param id="1" name="Comparison">0</param>
                            <param id="2" name="Value">1</param>
                        </condition>
                    </conditions>
                    <actions>
                        <action id="4" name="Set animation" sid="645133273026245" type="Spr_Office">
                            <param id="0" name="Animation">&quot;LeftLight&quot;</param>
                            <param id="1" name="From">1</param>
                        </action>
                    </actions>
                    <sub-events>
                        <event-block sid="408630882345746">
                            <conditions>
                                <condition id="-7" name="Compare instance variable" sid="686438674892201" type="OBJ_ButtonDoorLeft1">
                                    <param id="0" name="Instance variable">Porta</param>
                                    <param id="1" name="Comparison">0</param>
                                    <param id="2" name="Value">0</param>
                                </condition>
                            </conditions>
                            <actions>
                                <action id="4" name="Set animation" sid="904097897850250" type="Spr_LeftBotoes">
                                    <param id="0" name="Animation">&quot;OnlyLight&quot;</param>
                                    <param id="1" name="From">1</param>
                                </action>
                            </actions>
                        </event-block>
                        <event-block sid="352586976870037">
                            <conditions>
                                <condition id="-7" name="Compare instance variable" sid="912465791478172" type="OBJ_ButtonDoorLeft1">
                                    <param id="0" name="Instance variable">Porta</param>
                                    <param id="1" name="Comparison">0</param>
                                    <param id="2" name="Value">1</param>
                                </condition>
                            </conditions>
                            <actions>
                                <action id="4" name="Set animation" sid="326164457877426" type="Spr_LeftBotoes">
                                    <param id="0" name="Animation">&quot;Both&quot;</param>
                                    <param id="1" name="From">1</param>
                                </action>
                            </actions>
                        </event-block>
                        <event-block sid="300992715498841">
                            <conditions />
                            <actions />
                        </event-block>
                        <event-block sid="623174590608414">
                            <conditions>
                                <condition id="-7" name="Compare instance variable" sid="286555204600055" type="OBJ_ButtonDoorRight1">
                                    <param id="0" name="Instance variable">porta</param>
                                    <param id="1" name="Comparison">0</param>
                                    <param id="2" name="Value">0</param>
                                </condition>
                            </conditions>
                            <actions>
                                <action id="4" name="Set animation" sid="237649360409214" type="Spr_RightBotoes">
                                    <param id="0" name="Animation">&quot;Default&quot;</param>
                                    <param id="1" name="From">1</param>
                                </action>
                            </actions>
                        </event-block>
                        <event-block sid="189873362698682">
                            <conditions>
                                <condition id="-7" name="Compare instance variable" sid="741999376237689" type="OBJ_ButtonDoorRight1">
                                    <param id="0" name="Instance variable">porta</param>
                                    <param id="1" name="Comparison">0</param>
                                    <param id="2" name="Value">1</param>
                                </condition>
                            </conditions>
                            <actions>
                                <action id="4" name="Set animation" sid="729555698822446" type="Spr_RightBotoes">
                                    <param id="0" name="Animation">&quot;OnlyDoor&quot;</param>
                                    <param id="1" name="From">1</param>
                                </action>
                            </actions>
                        </event-block>
                    </sub-events>
                </event-block>
                <event-block sid="423693494162105">
                    <conditions>
                        <condition id="-7" name="Compare instance variable" sid="327171476077796" type="Spr_Office">
                            <param id="0" name="Instance variable">ladodaluz</param>
                            <param id="1" name="Comparison">0</param>
                            <param id="2" name="Value">2</param>
                        </condition>
                    </conditions>
                    <actions>
                        <action id="4" name="Set animation" sid="915751725527187" type="Spr_Office">
                            <param id="0" name="Animation">&quot;RightLight&quot;</param>
                            <param id="1" name="From">1</param>
                        </action>
                    </actions>
                    <sub-events>
                        <event-block sid="810978287555300">
                            <conditions>
                                <condition id="-7" name="Compare instance variable" sid="124760476411497" type="OBJ_ButtonDoorRight1">
                                    <param id="0" name="Instance variable">porta</param>
                                    <param id="1" name="Comparison">0</param>
                                    <param id="2" name="Value">0</param>
                                </condition>
                            </conditions>
                            <actions>
                                <action id="4" name="Set animation" sid="292908824551566" type="Spr_RightBotoes">
                                    <param id="0" name="Animation">&quot;OnlyLight&quot;</param>
                                    <param id="1" name="From">1</param>
                                </action>
                            </actions>
                        </event-block>
                        <event-block sid="104124952724867">
                            <conditions>
                                <condition id="-7" name="Compare instance variable" sid="178182155565929" type="OBJ_ButtonDoorRight1">
                                    <param id="0" name="Instance variable">porta</param>
                                    <param id="1" name="Comparison">0</param>
                                    <param id="2" name="Value">1</param>
                                </condition>
                            </conditions>
                            <actions>
                                <action id="4" name="Set animation" sid="729139029455787" type="Spr_RightBotoes">
                                    <param id="0" name="Animation">&quot;Both&quot;</param>
                                    <param id="1" name="From">1</param>
                                </action>
                            </actions>
                        </event-block>
                        <event-block sid="990226683102040">
                            <conditions />
                            <actions />
                        </event-block>
                        <event-block sid="317667211055760">
                            <conditions>
                                <condition id="-7" name="Compare instance variable" sid="585598809910277" type="OBJ_ButtonDoorLeft1">
                                    <param id="0" name="Instance variable">Porta</param>
                                    <param id="1" name="Comparison">0</param>
                                    <param id="2" name="Value">0</param>
                                </condition>
                            </conditions>
                            <actions>
                                <action id="4" name="Set animation" sid="182725984778765" type="Spr_LeftBotoes">
                                    <param id="0" name="Animation">&quot;Default&quot;</param>
                                    <param id="1" name="From">1</param>
                                </action>
                            </actions>
                        </event-block>
                        <event-block sid="363078978960307">
                            <conditions>
                                <condition id="-7" name="Compare instance variable" sid="761279162469851" type="OBJ_ButtonDoorLeft1">
                                    <param id="0" name="Instance variable">Porta</param>
                                    <param id="1" name="Comparison">0</param>
                                    <param id="2" name="Value">1</param>
                                </condition>
                            </conditions>
                            <actions>
                                <action id="4" name="Set animation" sid="489561725909982" type="Spr_LeftBotoes">
                                    <param id="0" name="Animation">&quot;OnlyDoor&quot;</param>
                                    <param id="1" name="From">1</param>
                                </action>
                            </actions>
                        </event-block>
                    </sub-events>
                </event-block>
            </sub-events>
        </event-group>
        <event-group description="" sid="225815388871019" title="scroll">
            <sub-events>
                <event-block sid="599699771142291">
                    <conditions>
                        <condition id="-1" name="Every tick" sid="414349678340581" type="System" />
                        <condition id="-20" inverted="1" name="Is on mobile device" sid="173026193296529" type="System" />
                    </conditions>
                    <actions>
                        <action id="-3" name="Set position" sid="630398460055513" type="MouseBruh">
                            <param id="0" name="X">Mouse.X</param>
                            <param id="1" name="Y">Mouse.Y</param>
                        </action>
                    </actions>
                </event-block>
            </sub-events>
        </event-group>
        <event-group description="" sid="416691035572944" title="mobile control">
            <sub-events>
                <event-group description="" sid="400607907719588" title="Desaparecer os controles + flash">
                    <sub-events>
                        <event-block sid="394922937120037">
                            <conditions>
                                <condition id="-2" name="On start of layout" sid="122159336992004" type="System" />
                            </conditions>
                            <actions>
                                <action behavior="Flash" id="0" name="Flash" sid="173702330594744" type="C_Mobile">
                                    <param id="0" name="&apos;On&apos; time">0.5</param>
                                    <param id="1" name="&apos;Off&apos; time">0.5</param>
                                    <param id="2" name="Duration">5</param>
                                </action>
                            </actions>
                        </event-block>
                        <event-block sid="646568334847803">
                            <conditions>
                                <condition behavior="Flash" id="1" name="On flash ended" sid="579317970294877" type="C_Mobile" />
                            </conditions>
                            <actions>
                                <action id="-15" name="Set visible" sid="144732755253463" type="C_Mobile">
                                    <param id="0" name="Visibility">0</param>
                                </action>
                            </actions>
                        </event-block>
                    </sub-events>
                </event-group>
                <event-block sid="885461409918815">
                    <conditions>
                        <condition id="-20" inverted="1" name="Is on mobile device" sid="359400063221985" type="System" />
                    </conditions>
                    <actions>
                        <action id="-9" name="Destroy" sid="179887359205990" type="OBJ_TurnLeft" />
                        <action id="-9" name="Destroy" sid="545326916798551" type="OBJ_TurnRight" />
                    </actions>
                </event-block>
                <event-block sid="796403895700392">
                    <conditions>
                        <condition id="-20" name="Is on mobile device" sid="320109949772642" type="System" />
                    </conditions>
                    <actions>
                        <action behavior="ScrollTo" id="1" name="Set enabled" sid="889600635758639" type="Scroll">
                            <param id="0" name="State">0</param>
                        </action>
                        <action id="-3" name="Set position" sid="629762170988909" type="MouseBruh">
                            <param id="0" name="X">lerp(Self.X,Scroll.X,0.03)</param>
                            <param id="1" name="Y">lerp(Self.Y,Scroll.Y,1)</param>
                        </action>
                    </actions>
                </event-block>
                <event-block sid="848376800254503">
                    <conditions>
                        <condition id="4" name="Is touching object" sid="874651038918598" type="Touch">
                            <param id="0" name="Object">OBJ_TurnLeft</param>
                        </condition>
                        <condition id="4" inverted="1" name="Is touching object" sid="306026330080673" type="Touch">
                            <param id="0" name="Object">Spr_BotãoPainel</param>
                        </condition>
                    </conditions>
                    <actions>
                        <action behavior="8Direction" disabled="1" id="7" name="Simulate control" sid="760539062458569" type="Scroll">
                            <param id="0" name="Control">0</param>
                        </action>
                        <action id="-1" name="Set X" sid="344195528862849" type="Scroll">
                            <param id="0" name="X">0</param>
                        </action>
                    </actions>
                </event-block>
                <event-block sid="418521423844231">
                    <conditions>
                        <condition id="4" name="Is touching object" sid="115966409512962" type="Touch">
                            <param id="0" name="Object">OBJ_TurnRight</param>
                        </condition>
                        <condition id="4" inverted="1" name="Is touching object" sid="484393379041096" type="Touch">
                            <param id="0" name="Object">Spr_BotãoPainel</param>
                        </condition>
                    </conditions>
                    <actions>
                        <action behavior="8Direction" disabled="1" id="7" name="Simulate control" sid="181090824360012" type="Scroll">
                            <param id="0" name="Control">1</param>
                        </action>
                        <action id="-1" name="Set X" sid="791033120958773" type="Scroll">
                            <param id="0" name="X">1200</param>
                        </action>
                    </actions>
                </event-block>
            </sub-events>
        </event-group>
        <event-block sid="292186941199174">
            <conditions>
                <condition id="0" name="On key pressed" sid="833837556371196" type="Keyboard">
                    <param id="0" name="Key">27</param>
                </condition>
            </conditions>
            <actions>
                <action id="1" name="Close" sid="708933014909606" type="Browser" />
            </actions>
        </event-block>
        <event-group description="" sid="445015104967354" title="Sistema de Cameras">
            <sub-events>
                <event-block sid="703429972329133">
                    <conditions>
                        <condition id="7" name="Cursor is over object" sid="501261182089466" type="Mouse">
                            <param id="0" name="Object">Spr_BotãoPainel</param>
                        </condition>
                        <condition id="-7" name="Compare instance variable" sid="155148947946211" type="Spr_BotãoPainel">
                            <param id="0" name="Instance variable">selectbar</param>
                            <param id="1" name="Comparison">0</param>
                            <param id="2" name="Value">0</param>
                        </condition>
                        <condition id="-20" inverted="1" name="Is on mobile device" sid="579691931616007" type="System" />
                        <condition id="-7" name="Compare instance variable" sid="209459812868000" type="Hora">
                            <param id="0" name="Instance variable">Hora</param>
                            <param id="1" name="Comparison">1</param>
                            <param id="2" name="Value">6</param>
                        </condition>
                    </conditions>
                    <actions>
                        <action id="-10" name="Set value" sid="106477319329615" type="Spr_BotãoPainel">
                            <param id="0" name="Instance variable">selectbar</param>
                            <param id="1" name="Value">1</param>
                        </action>
                    </actions>
                    <sub-events>
                        <event-block sid="299151171558664">
                            <conditions>
                                <condition id="2" name="Is playing" sid="186806455238229" type="Spr_Painel">
                                    <param id="0" name="Animation">&quot;Animation2&quot;</param>
                                </condition>
                                <condition id="3" name="Compare frame" sid="502597817922436" type="Spr_Painel">
                                    <param id="0" name="Comparison">0</param>
                                    <param id="1" name="Number">12</param>
                                </condition>
                            </conditions>
                            <actions>
                                <action id="4" name="Set animation" sid="108099991011478" type="Spr_Painel">
                                    <param id="0" name="Animation">&quot;Default&quot;</param>
                                    <param id="1" name="From">1</param>
                                </action>
                                <action id="-11" name="Add to" sid="609641719706752" type="UsoDeEnergiaPRGS">
                                    <param id="0" name="Instance variable">NivelEnergia</param>
                                    <param id="1" name="Value">1</param>
                                </action>
                                <action id="0" name="Play" sid="720173607045991" type="Audio">
                                    <param id="0" name="Audio file">OpenCloseCamera</param>
                                    <param id="2" name="Loop">0</param>
                                    <param id="3" name="Volume">0</param>
                                    <param id="1" name="Tag (optional)">&quot;&quot;</param>
                                </action>
                            </actions>
                        </event-block>
                        <event-block sid="990470242934400">
                            <conditions>
                                <condition id="2" name="Is playing" sid="950805693916345" type="Spr_Painel">
                                    <param id="0" name="Animation">&quot;Default&quot;</param>
                                </condition>
                                <condition id="3" name="Compare frame" sid="222136645994183" type="Spr_Painel">
                                    <param id="0" name="Comparison">0</param>
                                    <param id="1" name="Number">12</param>
                                </condition>
                            </conditions>
                            <actions>
                                <action id="4" name="Set animation" sid="479498401010772" type="Spr_Painel">
                                    <param id="0" name="Animation">&quot;Animation2&quot;</param>
                                    <param id="1" name="From">1</param>
                                </action>
                                <action id="-12" name="Subtract from" sid="437100656143170" type="UsoDeEnergiaPRGS">
                                    <param id="0" name="Instance variable">NivelEnergia</param>
                                    <param id="1" name="Value">1</param>
                                </action>
                                <action id="0" name="Play" sid="431193758384917" type="Audio">
                                    <param id="0" name="Audio file">OpenCloseCamera</param>
                                    <param id="2" name="Loop">0</param>
                                    <param id="3" name="Volume">0</param>
                                    <param id="1" name="Tag (optional)">&quot;&quot;</param>
                                </action>
                            </actions>
                        </event-block>
                    </sub-events>
                </event-block>
                <event-block sid="194667763954939">
                    <conditions>
                        <condition id="4" name="Is touching object" sid="113008768229467" type="Touch">
                            <param id="0" name="Object">Spr_BotãoPainel</param>
                        </condition>
                        <condition id="-7" name="Compare instance variable" sid="201445452257050" type="Spr_BotãoPainel">
                            <param id="0" name="Instance variable">selectbar</param>
                            <param id="1" name="Comparison">0</param>
                            <param id="2" name="Value">0</param>
                        </condition>
                        <condition id="-20" name="Is on mobile device" sid="750791953978992" type="System" />
                        <condition id="-7" name="Compare instance variable" sid="447773609892711" type="Hora">
                            <param id="0" name="Instance variable">Hora</param>
                            <param id="1" name="Comparison">1</param>
                            <param id="2" name="Value">6</param>
                        </condition>
                    </conditions>
                    <actions>
                        <action id="-10" name="Set value" sid="171239052519686" type="Spr_BotãoPainel">
                            <param id="0" name="Instance variable">selectbar</param>
                            <param id="1" name="Value">1</param>
                        </action>
                    </actions>
                    <sub-events>
                        <event-block sid="126497562319743">
                            <conditions>
                                <condition id="2" name="Is playing" sid="590585468228701" type="Spr_Painel">
                                    <param id="0" name="Animation">&quot;Animation2&quot;</param>
                                </condition>
                                <condition id="3" name="Compare frame" sid="284744693659741" type="Spr_Painel">
                                    <param id="0" name="Comparison">0</param>
                                    <param id="1" name="Number">12</param>
                                </condition>
                            </conditions>
                            <actions>
                                <action id="4" name="Set animation" sid="354820850305786" type="Spr_Painel">
                                    <param id="0" name="Animation">&quot;Default&quot;</param>
                                    <param id="1" name="From">1</param>
                                </action>
                                <action id="-11" name="Add to" sid="237412284173319" type="UsoDeEnergiaPRGS">
                                    <param id="0" name="Instance variable">NivelEnergia</param>
                                    <param id="1" name="Value">1</param>
                                </action>
                                <action id="0" name="Play" sid="290126383337168" type="Audio">
                                    <param id="0" name="Audio file">OpenCloseCamera</param>
                                    <param id="2" name="Loop">0</param>
                                    <param id="3" name="Volume">0</param>
                                    <param id="1" name="Tag (optional)">&quot;&quot;</param>
                                </action>
                            </actions>
                        </event-block>
                        <event-block sid="894060353566259">
                            <conditions>
                                <condition id="2" name="Is playing" sid="979980068351115" type="Spr_Painel">
                                    <param id="0" name="Animation">&quot;Default&quot;</param>
                                </condition>
                                <condition id="3" name="Compare frame" sid="460306071307741" type="Spr_Painel">
                                    <param id="0" name="Comparison">0</param>
                                    <param id="1" name="Number">12</param>
                                </condition>
                            </conditions>
                            <actions>
                                <action id="4" name="Set animation" sid="138388051463840" type="Spr_Painel">
                                    <param id="0" name="Animation">&quot;Animation2&quot;</param>
                                    <param id="1" name="From">1</param>
                                </action>
                                <action id="-12" name="Subtract from" sid="301696446150175" type="UsoDeEnergiaPRGS">
                                    <param id="0" name="Instance variable">NivelEnergia</param>
                                    <param id="1" name="Value">1</param>
                                </action>
                                <action id="0" name="Play" sid="615805106977299" type="Audio">
                                    <param id="0" name="Audio file">OpenCloseCamera</param>
                                    <param id="2" name="Loop">0</param>
                                    <param id="3" name="Volume">0</param>
                                    <param id="1" name="Tag (optional)">&quot;&quot;</param>
                                </action>
                            </actions>
                        </event-block>
                    </sub-events>
                </event-block>
                <event-block sid="931487499675885">
                    <conditions>
                        <condition id="7" inverted="1" name="Cursor is over object" sid="626045879505001" type="Mouse">
                            <param id="0" name="Object">Spr_BotãoPainel</param>
                        </condition>
                        <condition id="-7" name="Compare instance variable" sid="166756634265375" type="Spr_BotãoPainel">
                            <param id="0" name="Instance variable">selectbar</param>
                            <param id="1" name="Comparison">0</param>
                            <param id="2" name="Value">1</param>
                        </condition>
                    </conditions>
                    <actions>
                        <action id="-10" name="Set value" sid="647875176040685" type="Spr_BotãoPainel">
                            <param id="0" name="Instance variable">selectbar</param>
                            <param id="1" name="Value">0</param>
                        </action>
                    </actions>
                </event-block>
                <event-block sid="231326376525254">
                    <conditions>
                        <condition id="2" name="Is playing" sid="253833571403451" type="Spr_Painel">
                            <param id="0" name="Animation">&quot;Animation2&quot;</param>
                        </condition>
                    </conditions>
                    <actions />
                    <sub-events>
                        <event-block sid="550387401960471">
                            <conditions>
                                <condition id="3" name="Compare frame" sid="258441136365923" type="Spr_Painel">
                                    <param id="0" name="Comparison">0</param>
                                    <param id="1" name="Number">0</param>
                                </condition>
                            </conditions>
                            <actions>
                                <action id="-4" name="Set layer visible" sid="189724395459849" type="System">
                                    <param id="0" name="Layer">2</param>
                                    <param id="1" name="Visibility">1</param>
                                </action>
                            </actions>
                        </event-block>
                        <event-block sid="960323596597823">
                            <conditions>
                                <condition id="3" name="Compare frame" sid="436112918535667" type="Spr_Painel">
                                    <param id="0" name="Comparison">1</param>
                                    <param id="1" name="Number">0</param>
                                </condition>
                            </conditions>
                            <actions>
                                <action id="-4" name="Set layer visible" sid="902568238088960" type="System">
                                    <param id="0" name="Layer">2</param>
                                    <param id="1" name="Visibility">0</param>
                                </action>
                            </actions>
                        </event-block>
                    </sub-events>
                </event-block>
                <event-block sid="196872485632230">
                    <conditions>
                        <condition id="2" name="Is playing" sid="262050311377593" type="Spr_Painel">
                            <param id="0" name="Animation">&quot;Default&quot;</param>
                        </condition>
                    </conditions>
                    <actions />
                    <sub-events>
                        <event-block sid="772391333511895">
                            <conditions>
                                <condition id="3" name="Compare frame" sid="573105153220536" type="Spr_Painel">
                                    <param id="0" name="Comparison">0</param>
                                    <param id="1" name="Number">12</param>
                                </condition>
                            </conditions>
                            <actions>
                                <action id="-4" name="Set layer visible" sid="436719475114442" type="System">
                                    <param id="0" name="Layer">2</param>
                                    <param id="1" name="Visibility">1</param>
                                </action>
                            </actions>
                        </event-block>
                        <event-block sid="752478325301055">
                            <conditions>
                                <condition id="3" name="Compare frame" sid="939332687645783" type="Spr_Painel">
                                    <param id="0" name="Comparison">1</param>
                                    <param id="1" name="Number">12</param>
                                </condition>
                            </conditions>
                            <actions>
                                <action id="-4" name="Set layer visible" sid="147232660311686" type="System">
                                    <param id="0" name="Layer">2</param>
                                    <param id="1" name="Visibility">0</param>
                                </action>
                            </actions>
                        </event-block>
                    </sub-events>
                </event-block>
            </sub-events>
        </event-group>
        <event-block sid="676254877752483">
            <conditions>
                <condition id="1" inverted="1" name="Is overlapping another object" sid="934884073823630" type="Scroll">
                    <param id="0" name="Object">MouseBruh</param>
                </condition>
                <condition id="-20" inverted="1" name="Is on mobile device" sid="449733485556134" type="System" />
            </conditions>
            <actions>
                <action id="-3" name="Set position" sid="624068435528794" type="Scroll">
                    <param id="0" name="X">lerp(Self.X,MouseBruh.X,0.2)</param>
                    <param id="1" name="Y">lerp(Self.Y,MouseBruh.Y,0.2)</param>
                </action>
            </actions>
        </event-block>
        <event-group description="" sid="793517228741993" title="Nariz do Freddy">
            <sub-events>
                <event-block sid="235389874756527">
                    <conditions>
                        <condition id="17" name="On tap object" sid="199208203527221" type="Touch">
                            <param id="0" name="Object">OBJ_NarizDoFedy</param>
                        </condition>
                        <condition id="-9" inverted="1" name="Layer is visible" sid="127676589876739" type="System">
                            <param id="0" name="Layer">2</param>
                        </condition>
                    </conditions>
                    <actions>
                        <action id="0" name="Play" sid="765007484674393" type="Audio">
                            <param id="0" name="Audio file">NarizDoFedy</param>
                            <param id="2" name="Loop">0</param>
                            <param id="3" name="Volume">0</param>
                            <param id="1" name="Tag (optional)">&quot;&quot;</param>
                        </action>
                    </actions>
                </event-block>
            </sub-events>
        </event-group>
        <event-group description="" sid="478700451713114" title="UsoDeEnergia">
            <sub-events>
                <event-block sid="644766466831541">
                    <conditions>
                        <condition id="-1" name="Every tick" sid="994458546181173" type="System" />
                    </conditions>
                    <actions>
                        <action id="5" name="Set frame" sid="424364535065007" type="UsoDeEnergiaPRGS">
                            <param id="0" name="Frame number">UsoDeEnergiaPRGS.NivelEnergia</param>
                        </action>
                    </actions>
                </event-block>
                <event-block sid="632924670111843">
                    <conditions>
                        <condition id="-7" name="Compare instance variable" sid="575296956690583" type="UsoDeEnergiaPRGS">
                            <param id="0" name="Instance variable">NivelEnergia</param>
                            <param id="1" name="Comparison">2</param>
                            <param id="2" name="Value">0</param>
                        </condition>
                    </conditions>
                    <actions>
                        <action id="-10" name="Set value" sid="260625134988518" type="UsoDeEnergiaPRGS">
                            <param id="0" name="Instance variable">NivelEnergia</param>
                            <param id="1" name="Value">0</param>
                        </action>
                    </actions>
                </event-block>
                <event-block sid="799824381173027">
                    <conditions>
                        <condition id="-7" name="Compare instance variable" sid="678713133979220" type="UsoDeEnergiaPRGS">
                            <param id="0" name="Instance variable">NivelEnergia</param>
                            <param id="1" name="Comparison">4</param>
                            <param id="2" name="Value">4</param>
                        </condition>
                    </conditions>
                    <actions>
                        <action id="-10" name="Set value" sid="743697182975639" type="UsoDeEnergiaPRGS">
                            <param id="0" name="Instance variable">NivelEnergia</param>
                            <param id="1" name="Value">4</param>
                        </action>
                    </actions>
                </event-block>
            </sub-events>
        </event-group>
        <event-block sid="621321728575241">
            <conditions>
                <condition id="-2" name="On start of layout" sid="366782845208255" type="System" />
            </conditions>
            <actions>
                <action id="0" name="Play" sid="147812428923525" type="Audio">
                    <param id="0" name="Audio file">FAN and Light</param>
                    <param id="2" name="Loop">1</param>
                    <param id="3" name="Volume">-10</param>
                    <param id="1" name="Tag (optional)">&quot;fanlight&quot;</param>
                </action>
                <action id="-16" name="Wait" sid="974763335414069" type="System">
                    <param id="0" name="Seconds">4.5</param>
                </action>
                <action id="0" name="Play" sid="258962785339431" type="Audio">
                    <param id="0" name="Audio file">voiceover1c</param>
                    <param id="2" name="Loop">0</param>
                    <param id="3" name="Volume">0</param>
                    <param id="1" name="Tag (optional)">&quot;night1call&quot;</param>
                </action>
            </actions>
        </event-block>
        <event-group description="" sid="247877410135788" title="Hora">
            <sub-events>
                <event-block sid="144754161193163">
                    <conditions>
                        <condition id="-6" name="Every X seconds" sid="794247512143699" type="System">
                            <param id="0" name="Interval (seconds)">45</param>
                        </condition>
                    </conditions>
                    <actions>
                        <action id="-11" name="Add to" sid="764914085630752" type="Hora">
                            <param id="0" name="Instance variable">Hora</param>
                            <param id="1" name="Value">1</param>
                        </action>
                    </actions>
                </event-block>
                <event-block sid="991420165614189">
                    <conditions>
                        <condition id="-1" name="Every tick" sid="708008367771716" type="System" />
                    </conditions>
                    <actions>
                        <action id="5" name="Set frame" sid="450208228718421" type="Hora">
                            <param id="0" name="Frame number">self.Hora</param>
                        </action>
                    </actions>
                </event-block>
            </sub-events>
        </event-group>
        <event-group description="" sid="168142254068465" title="6AM">
            <sub-events>
                <event-block sid="458655614941544">
                    <conditions>
                        <condition id="-7" name="Compare instance variable" sid="792347176205953" type="Hora">
                            <param id="0" name="Instance variable">Hora</param>
                            <param id="1" name="Comparison">0</param>
                            <param id="2" name="Value">6</param>
                        </condition>
                        <condition id="-4" name="Trigger once while true" sid="292685165259574" type="System" />
                    </conditions>
                    <actions>
                        <action behavior="Fade" id="1" name="Start fade" sid="852087281734456" type="Spr_FadeIn" />
                        <action id="6" name="Stop" sid="940288993277537" type="Audio">
                            <param id="0" name="Tag">&quot;fanlight&quot;</param>
                        </action>
                        <action id="6" name="Stop" sid="461351302042441" type="Audio">
                            <param id="0" name="Tag">&quot;lamp&quot;</param>
                        </action>
                        <action id="6" name="Stop" sid="324001081791959" type="Audio">
                            <param id="0" name="Tag">&quot;night1call&quot;</param>
                        </action>
                    </actions>
                </event-block>
                <event-block sid="481600423793477">
                    <conditions>
                        <condition behavior="Fade" id="2" name="On wait finished" sid="908680961668614" type="Spr_FadeIn" />
                    </conditions>
                    <actions>
                        <action id="-4" name="Set layer visible" sid="420519750646867" type="System">
                            <param id="0" name="Layer">&quot;6AM&quot;</param>
                            <param id="1" name="Visibility">1</param>
                        </action>
                    </actions>
                </event-block>
                <event-block sid="687435663389240">
                    <conditions>
                        <condition id="-9" name="Layer is visible" sid="980064853144663" type="System">
                            <param id="0" name="Layer">&quot;6AM&quot;</param>
                        </condition>
                        <condition id="-4" name="Trigger once while true" sid="312721395944546" type="System" />
                    </conditions>
                    <actions>
                        <action id="0" name="Play" sid="806293939107218" type="Audio">
                            <param id="0" name="Audio file">Clock</param>
                            <param id="2" name="Loop">0</param>
                            <param id="3" name="Volume">0</param>
                            <param id="1" name="Tag (optional)">&quot;clock&quot;</param>
                        </action>
                        <action behavior="Pin" id="0" name="Pin to object" sid="257595310606316" type="6AMTXT2">
                            <param id="0" name="Pin to">6AMTXT</param>
                            <param id="1" name="Mode">0</param>
                        </action>
                        <action behavior="MoveTo" id="4" name="Move to XY" sid="854811458784459" type="6AMTXT">
                            <param id="0" name="X">Self.X</param>
                            <param id="1" name="Y">125</param>
                        </action>
                    </actions>
                </event-block>
                <event-block sid="896517571705322">
                    <conditions>
                        <condition behavior="MoveTo" id="0" name="On hit target position" sid="878793746144916" type="6AMTXT" />
                    </conditions>
                    <actions>
                        <action id="0" name="Play" sid="518599818186459" type="Audio">
                            <param id="0" name="Audio file">Children</param>
                            <param id="2" name="Loop">0</param>
                            <param id="3" name="Volume">0</param>
                            <param id="1" name="Tag (optional)">&quot;children&quot;</param>
                        </action>
                    </actions>
                </event-block>
                <event-block sid="383528406681654">
                    <conditions>
                        <condition id="0" name="On ended" sid="449987079059685" type="Audio">
                            <param id="0" name="Tag">&quot;clock&quot;</param>
                        </condition>
                    </conditions>
                    <actions>
                        <action id="-2" name="Go to layout" sid="395258726075433" type="System">
                            <param id="0" name="Layout">Menu Principal</param>
                        </action>
                    </actions>
                </event-block>
                <event-block sid="784563010968011">
                    <conditions>
                        <condition id="0" name="On key pressed" sid="151792926735944" type="Keyboard">
                            <param id="0" name="Key">54</param>
                        </condition>
                        <condition id="-18" name="Is in preview" sid="394114789955178" type="System" />
                    </conditions>
                    <actions>
                        <action id="-10" name="Set value" sid="564364078403754" type="Hora">
                            <param id="0" name="Instance variable">Hora</param>
                            <param id="1" name="Value">6</param>
                        </action>
                    </actions>
                </event-block>
            </sub-events>
        </event-group>
        <event-group description="" sid="900384941349068" title="Barulho da Luz">
            <sub-events>
                <event-block sid="399130997078647">
                    <conditions>
                        <condition id="2" name="Is playing" sid="786513916379244" type="Spr_Office">
                            <param id="0" name="Animation">&quot;Default&quot;</param>
                        </condition>
                        <condition id="-4" name="Trigger once while true" sid="589139917376775" type="System" />
                    </conditions>
                    <actions>
                        <action id="6" name="Stop" sid="716048689609816" type="Audio">
                            <param id="0" name="Tag">&quot;lamp&quot;</param>
                        </action>
                    </actions>
                </event-block>
                <event-block sid="779753980788462">
                    <conditions>
                        <condition id="2" inverted="1" name="Is playing" sid="137570053396899" type="Spr_Office">
                            <param id="0" name="Animation">&quot;Default&quot;</param>
                        </condition>
                        <condition id="-4" name="Trigger once while true" sid="799529315378976" type="System" />
                    </conditions>
                    <actions>
                        <action id="0" name="Play" sid="351896349623020" type="Audio">
                            <param id="0" name="Audio file">Lamps</param>
                            <param id="2" name="Loop">1</param>
                            <param id="3" name="Volume">0</param>
                            <param id="1" name="Tag (optional)">&quot;lamp&quot;</param>
                        </action>
                    </actions>
                </event-block>
            </sub-events>
        </event-group>
        <event-group description="" sid="158575958891702" title="Mapa">
            <sub-events>
                <event-group description="" sid="475714596651590" title="Mudar">
                    <sub-events>
                        <event-block sid="734002660893165">
                            <conditions>
                                <condition id="17" name="On tap object" sid="987844676436543" type="Touch">
                                    <param id="0" name="Object">Cam_C</param>
                                </condition>
                                <condition id="-9" name="Layer is visible" sid="637156941521852" type="System">
                                    <param id="0" name="Layer">2</param>
                                </condition>
                                <condition id="-7" name="Compare instance variable" sid="759635058967786" type="Hora">
                                    <param id="0" name="Instance variable">Hora</param>
                                    <param id="1" name="Comparison">1</param>
                                    <param id="2" name="Value">6</param>
                                </condition>
                            </conditions>
                            <actions>
                                <action id="4" name="Set animation" sid="473707692132867" type="Spr_StageCamera">
                                    <param id="0" name="Animation">Cam_C.Cam</param>
                                    <param id="1" name="From">1</param>
                                </action>
                                <action id="4" name="Set animation" sid="797789180532812" type="Obj_CamMap">
                                    <param id="0" name="Animation">Cam_C.Cam</param>
                                    <param id="1" name="From">1</param>
                                </action>
                                <action id="0" name="Play" sid="316550105675887" type="Audio">
                                    <param id="0" name="Audio file">ChangeCamera</param>
                                    <param id="2" name="Loop">0</param>
                                    <param id="3" name="Volume">0</param>
                                    <param id="1" name="Tag (optional)">&quot;&quot;</param>
                                </action>
                            </actions>
                        </event-block>
                    </sub-events>
                </event-group>
                <event-group description="" sid="168999489188721" title="Aparece">
                    <sub-events>
                        <event-block sid="405984764477993">
                            <conditions>
                                <condition id="-9" name="Layer is visible" sid="473413101781882" type="System">
                                    <param id="0" name="Layer">&quot;Painel de cameras0&quot;</param>
                                </condition>
                            </conditions>
                            <actions>
                                <action id="-15" name="Set visible" sid="174563486933137" type="Obj_CamMap">
                                    <param id="0" name="Visibility">1</param>
                                </action>
                            </actions>
                        </event-block>
                        <event-block sid="475820563306356">
                            <conditions>
                                <condition id="-9" inverted="1" name="Layer is visible" sid="775228397514084" type="System">
                                    <param id="0" name="Layer">&quot;Painel de cameras0&quot;</param>
                                </condition>
                            </conditions>
                            <actions>
                                <action id="-15" name="Set visible" sid="908151418374092" type="Obj_CamMap">
                                    <param id="0" name="Visibility">0</param>
                                </action>
                            </actions>
                        </event-block>
                    </sub-events>
                </event-group>
            </sub-events>
        </event-group>
    </events>
</c2eventsheet>
